logai/__init__.py
logai/config_interfaces.py
logai/algorithms/__init__.py
logai/algorithms/algo_interfaces.py
logai/algorithms/factory.py
logai/algorithms/anomaly_detection_algo/__init__.py
logai/algorithms/anomaly_detection_algo/anomaly_detector_het.py
logai/algorithms/anomaly_detection_algo/dbl.py
logai/algorithms/anomaly_detection_algo/distribution_divergence.py
logai/algorithms/anomaly_detection_algo/ets.py
logai/algorithms/anomaly_detection_algo/forecast_nn.py
logai/algorithms/anomaly_detection_algo/isolation_forest.py
logai/algorithms/anomaly_detection_algo/local_outlier_factor.py
logai/algorithms/anomaly_detection_algo/logbert.py
logai/algorithms/anomaly_detection_algo/one_class_svm.py
logai/algorithms/categorical_encoding_algo/__init__.py
logai/algorithms/categorical_encoding_algo/label_encoding.py
logai/algorithms/categorical_encoding_algo/one_hot_encoding.py
logai/algorithms/categorical_encoding_algo/ordinal_encoding.py
logai/algorithms/clustering_algo/__init__.py
logai/algorithms/clustering_algo/birch.py
logai/algorithms/clustering_algo/dbscan.py
logai/algorithms/clustering_algo/kmeans.py
logai/algorithms/nn_model/__init__.py
logai/algorithms/nn_model/transformers.py
logai/algorithms/nn_model/forecast_nn/__init__.py
logai/algorithms/nn_model/forecast_nn/base_nn.py
logai/algorithms/nn_model/forecast_nn/cnn.py
logai/algorithms/nn_model/forecast_nn/lstm.py
logai/algorithms/nn_model/forecast_nn/transformer.py
logai/algorithms/nn_model/forecast_nn/utils.py
logai/algorithms/nn_model/logbert/__init__.py
logai/algorithms/nn_model/logbert/configs.py
logai/algorithms/nn_model/logbert/eval_metric_utils.py
logai/algorithms/nn_model/logbert/predict.py
logai/algorithms/nn_model/logbert/predict_utils.py
logai/algorithms/nn_model/logbert/tokenizer_utils.py
logai/algorithms/nn_model/logbert/train.py
logai/algorithms/parsing_algo/__init__.py
logai/algorithms/parsing_algo/ael.py
logai/algorithms/parsing_algo/drain.py
logai/algorithms/parsing_algo/iplom.py
logai-0.1.5.dist-info/LICENSE.txt
logai-0.1.5.dist-info/METADATA
logai-0.1.5.dist-info/WHEEL
logai-0.1.5.dist-info/top_level.txt
logai-0.1.5.dist-info/RECORD
