Metadata-Version: 2.1
Name: logai
Version: 0.1.5
Summary: LogAI is unified framework for AI-based log analytics
Author: Qian Cheng, Amrita Saha, Wenzhuo Yang, Chenghao Liu, Gerald Woo, Doyen Sahoo, Steven Hoi
Author-email: logai@salesforce.com
License: BSD 3-Clause License
Requires-Python: >=3.7.0,<4
License-File: LICENSE.txt
Requires-Dist: schema (>=0.7.5)
Requires-Dist: salesforce-merlion (>=1.0.0)
Requires-Dist: Cython (>=0.29.30)
Requires-Dist: nltk (>=3.6.5)
Requires-Dist: gensim (>=4.1.2)
Requires-Dist: scikit-learn (>=1.0.1)
Requires-Dist: pandas (>=1.2.0)
Requires-Dist: numpy (>=1.21.4)
Requires-Dist: spacy (>=3.2.2)
Requires-Dist: attrs (>=21.2.0)
Requires-Dist: dataclasses (>=0.6)
Requires-Dist: PyYAML (>=6.0)
Requires-Dist: tqdm (>=4.62.3)
Requires-Dist: cachetools (>=4.2.4)
Requires-Dist: matplotlib (>=3.5.1)
Requires-Dist: seaborn (>=0.11.2)
Requires-Dist: Jinja2 (>=3.0.0)
Requires-Dist: numba (>=0.56.3)
Provides-Extra: all
Requires-Dist: dash-bootstrap-components (>=1.2.1) ; extra == 'all'
Requires-Dist: plotly (>=5.9.0) ; extra == 'all'
Requires-Dist: dash (>=2.5.1) ; extra == 'all'
Requires-Dist: tokenizers (>=0.11.6) ; extra == 'all'
Requires-Dist: datasets (>=1.18.3) ; extra == 'all'
Requires-Dist: torch (>=1.10.1) ; extra == 'all'
Requires-Dist: transformers (<=4.23,>=4.17.0) ; extra == 'all'
Requires-Dist: Sphinx (>=3.5.3) ; extra == 'all'
Requires-Dist: docutils (>=0.18.1) ; extra == 'all'
Requires-Dist: wheel (>=0.37.1) ; extra == 'all'
Requires-Dist: toml (>=0.10.2) ; extra == 'all'
Requires-Dist: build (>=0.7.0) ; extra == 'all'
Requires-Dist: jupyter (>=1.0.0) ; extra == 'all'
Requires-Dist: ipykernel (>=6.16) ; extra == 'all'
Requires-Dist: pytest (>=6.2.5) ; extra == 'all'
Provides-Extra: deep-learning
Requires-Dist: tokenizers (>=0.11.6) ; extra == 'deep-learning'
Requires-Dist: datasets (>=1.18.3) ; extra == 'deep-learning'
Requires-Dist: torch (>=1.10.1) ; extra == 'deep-learning'
Requires-Dist: transformers (<=4.23,>=4.17.0) ; extra == 'deep-learning'
Provides-Extra: dev
Requires-Dist: Sphinx (>=3.5.3) ; extra == 'dev'
Requires-Dist: docutils (>=0.18.1) ; extra == 'dev'
Requires-Dist: wheel (>=0.37.1) ; extra == 'dev'
Requires-Dist: toml (>=0.10.2) ; extra == 'dev'
Requires-Dist: build (>=0.7.0) ; extra == 'dev'
Requires-Dist: jupyter (>=1.0.0) ; extra == 'dev'
Requires-Dist: ipykernel (>=6.16) ; extra == 'dev'
Requires-Dist: pytest (>=6.2.5) ; extra == 'dev'
Provides-Extra: gui
Requires-Dist: dash-bootstrap-components (>=1.2.1) ; extra == 'gui'
Requires-Dist: plotly (>=5.9.0) ; extra == 'gui'
Requires-Dist: dash (>=2.5.1) ; extra == 'gui'
